konickname/__init__.py
konickname-0.1.0.dist-info/METADATA
konickname-0.1.0.dist-info/WHEEL
konickname-0.1.0.dist-info/RECORD
