Metadata-Version: 2.1
Name: konickname
Version: 0.1.0
Summary: 한국어 닉네임 랜덤 생성기
License: MIT
Author: sjquant
Author-email: seonujang92@gmail.com
Requires-Python: >=3.10,<4.0
Classifier: License :: OSI Approved :: MIT License
Classifier: Programming Language :: Python :: 3
Classifier: Programming Language :: Python :: 3.10
Classifier: Programming Language :: Python :: 3.11
Classifier: Programming Language :: Python :: 3.12
